<?xml version="1.0" encoding="UTF-8" ?>
<!DOCTYPE mapper PUBLIC "-//mybatis.org//DTD Mapper 3.0//EN" "http://mybatis.org/dtd/mybatis-3-mapper.dtd" >
<mapper namespace="xsscd.monitor.air.southwest.modules.job.entitys.mybatis.mapper.GWFactCityHourMapper" >
  <resultMap id="BaseResultMap" type="xsscd.monitor.air.southwest.modules.job.entitys.mybatis.dto.GWFactCityHour" >
    <!--
      WARNING - @mbggenerated
      This element is automatically generated by MyBatis Generator, do not modify.
    -->
    <id column="ID" property="iD" jdbcType="INTEGER" />
    <result column="datetime" property="datetime" jdbcType="TIMESTAMP" />
    <result column="citycode" property="citycode" jdbcType="INTEGER" />
    <result column="cityname" property="cityname" jdbcType="NVARCHAR" />
    <result column="stationcount" property="stationcount" jdbcType="INTEGER" />
    <result column="SO2" property="sO2" jdbcType="VARCHAR" />
    <result column="NO2" property="nO2" jdbcType="VARCHAR" />
    <result column="PM10" property="pM10" jdbcType="VARCHAR" />
    <result column="CO" property="cO" jdbcType="VARCHAR" />
    <result column="O3" property="o3" jdbcType="VARCHAR" />
    <result column="PM25" property="pM25" jdbcType="VARCHAR" />
    <result column="Chiefly_Infectant" property="chieflyInfectant" jdbcType="VARCHAR" />
    <result column="Grade" property="grade" jdbcType="VARCHAR" />
    <result column="GradeDescription" property="gradeDescription" jdbcType="NVARCHAR" />
    <result column="AQI" property="aQI" jdbcType="VARCHAR" />
    <result column="Color" property="color" jdbcType="NVARCHAR" />
    <result column="inputdate" property="inputdate" jdbcType="TIMESTAMP" />
  </resultMap>
  <sql id="Base_Column_List" >
    <!--
      WARNING - @mbggenerated
      This element is automatically generated by MyBatis Generator, do not modify.
    -->
    ID, datetime, citycode, cityname, stationcount, SO2, NO2, PM10, CO, O3, PM25, Chiefly_Infectant, 
    Grade, GradeDescription, AQI, Color, inputdate
  </sql>
  <sql id="Base_Where_Case" >
    <!--
      WARNING - @mbggenerated
      This element is automatically generated by MyBatis Generator, do not modify.
    -->
    <where >
      <if test="iD != null" >
         AND ID = #{iD,jdbcType=INTEGER}
      </if>
      <if test="datetime != null" >
         AND datetime = #{datetime,jdbcType=TIMESTAMP}
      </if>
      <if test="citycode != null" >
         AND citycode = #{citycode,jdbcType=INTEGER}
      </if>
      <if test="cityname != null" >
         AND cityname = #{cityname,jdbcType=NVARCHAR}
      </if>
      <if test="stationcount != null" >
         AND stationcount = #{stationcount,jdbcType=INTEGER}
      </if>
      <if test="sO2 != null" >
         AND SO2 = #{sO2,jdbcType=VARCHAR}
      </if>
      <if test="nO2 != null" >
         AND NO2 = #{nO2,jdbcType=VARCHAR}
      </if>
      <if test="pM10 != null" >
         AND PM10 = #{pM10,jdbcType=VARCHAR}
      </if>
      <if test="cO != null" >
         AND CO = #{cO,jdbcType=VARCHAR}
      </if>
      <if test="o3 != null" >
         AND O3 = #{o3,jdbcType=VARCHAR}
      </if>
      <if test="pM25 != null" >
         AND PM25 = #{pM25,jdbcType=VARCHAR}
      </if>
      <if test="chieflyInfectant != null" >
         AND Chiefly_Infectant = #{chieflyInfectant,jdbcType=VARCHAR}
      </if>
      <if test="grade != null" >
         AND Grade = #{grade,jdbcType=VARCHAR}
      </if>
      <if test="gradeDescription != null" >
         AND GradeDescription = #{gradeDescription,jdbcType=NVARCHAR}
      </if>
      <if test="aQI != null" >
         AND AQI = #{aQI,jdbcType=VARCHAR}
      </if>
      <if test="color != null" >
         AND Color = #{color,jdbcType=NVARCHAR}
      </if>
      <if test="inputdate != null" >
         AND inputdate = #{inputdate,jdbcType=TIMESTAMP}
      </if>
    </where>
  </sql>
  <select id="selectCount" resultType="java.lang.Long" parameterType="xsscd.monitor.air.southwest.modules.job.entitys.mybatis.dto.GWFactCityHour" >
    <!--
      WARNING - @mbggenerated
      This element is automatically generated by MyBatis Generator, do not modify.
    -->
    select count( ID)
     from GW_Fact_CityHour
    <include refid="Base_Where_Case" />
  </select>
  <select id="select" resultMap="BaseResultMap" parameterType="xsscd.monitor.air.southwest.modules.job.entitys.mybatis.dto.GWFactCityHour" >
    <!--
      WARNING - @mbggenerated
      This element is automatically generated by MyBatis Generator, do not modify.
    -->
    select 
    <include refid="Base_Column_List" />
     from GW_Fact_CityHour
    <include refid="Base_Where_Case" />
  </select>
  <select id="selectByPrimaryKey" resultMap="BaseResultMap" parameterType="java.lang.Integer" >
    <!--
      WARNING - @mbggenerated
      This element is automatically generated by MyBatis Generator, do not modify.
    -->
    select 
    <include refid="Base_Column_List" />
    from GW_Fact_CityHour
    where ID = #{iD,jdbcType=INTEGER}
  </select>
  <delete id="deleteByPrimaryKey" parameterType="java.lang.Integer" >
    <!--
      WARNING - @mbggenerated
      This element is automatically generated by MyBatis Generator, do not modify.
    -->
    delete from GW_Fact_CityHour
    where ID = #{iD,jdbcType=INTEGER}
  </delete>
  <insert id="insert" parameterType="xsscd.monitor.air.southwest.modules.job.entitys.mybatis.dto.GWFactCityHour" >
    <!--
      WARNING - @mbggenerated
      This element is automatically generated by MyBatis Generator, do not modify.
    -->
    insert into GW_Fact_CityHour (ID, datetime, citycode, 
      cityname, stationcount, SO2, 
      NO2, PM10, CO, O3, 
      PM25, Chiefly_Infectant, Grade, 
      GradeDescription, AQI, Color, 
      inputdate)
    values (#{iD,jdbcType=INTEGER}, #{datetime,jdbcType=TIMESTAMP}, #{citycode,jdbcType=INTEGER}, 
      #{cityname,jdbcType=NVARCHAR}, #{stationcount,jdbcType=INTEGER}, #{sO2,jdbcType=VARCHAR}, 
      #{nO2,jdbcType=VARCHAR}, #{pM10,jdbcType=VARCHAR}, #{cO,jdbcType=VARCHAR}, #{o3,jdbcType=VARCHAR}, 
      #{pM25,jdbcType=VARCHAR}, #{chieflyInfectant,jdbcType=VARCHAR}, #{grade,jdbcType=VARCHAR}, 
      #{gradeDescription,jdbcType=NVARCHAR}, #{aQI,jdbcType=VARCHAR}, #{color,jdbcType=NVARCHAR}, 
      #{inputdate,jdbcType=TIMESTAMP})
  </insert>
  <insert id="insertSelective" parameterType="xsscd.monitor.air.southwest.modules.job.entitys.mybatis.dto.GWFactCityHour" >
    <!--
      WARNING - @mbggenerated
      This element is automatically generated by MyBatis Generator, do not modify.
    -->
    insert into GW_Fact_CityHour
    <trim prefix="(" suffix=")" suffixOverrides="," >
      <if test="iD != null" >
        ID,
      </if>
      <if test="datetime != null" >
        datetime,
      </if>
      <if test="citycode != null" >
        citycode,
      </if>
      <if test="cityname != null" >
        cityname,
      </if>
      <if test="stationcount != null" >
        stationcount,
      </if>
      <if test="sO2 != null" >
        SO2,
      </if>
      <if test="nO2 != null" >
        NO2,
      </if>
      <if test="pM10 != null" >
        PM10,
      </if>
      <if test="cO != null" >
        CO,
      </if>
      <if test="o3 != null" >
        O3,
      </if>
      <if test="pM25 != null" >
        PM25,
      </if>
      <if test="chieflyInfectant != null" >
        Chiefly_Infectant,
      </if>
      <if test="grade != null" >
        Grade,
      </if>
      <if test="gradeDescription != null" >
        GradeDescription,
      </if>
      <if test="aQI != null" >
        AQI,
      </if>
      <if test="color != null" >
        Color,
      </if>
      <if test="inputdate != null" >
        inputdate,
      </if>
    </trim>
    <trim prefix="values (" suffix=")" suffixOverrides="," >
      <if test="iD != null" >
        #{iD,jdbcType=INTEGER},
      </if>
      <if test="datetime != null" >
        #{datetime,jdbcType=TIMESTAMP},
      </if>
      <if test="citycode != null" >
        #{citycode,jdbcType=INTEGER},
      </if>
      <if test="cityname != null" >
        #{cityname,jdbcType=NVARCHAR},
      </if>
      <if test="stationcount != null" >
        #{stationcount,jdbcType=INTEGER},
      </if>
      <if test="sO2 != null" >
        #{sO2,jdbcType=VARCHAR},
      </if>
      <if test="nO2 != null" >
        #{nO2,jdbcType=VARCHAR},
      </if>
      <if test="pM10 != null" >
        #{pM10,jdbcType=VARCHAR},
      </if>
      <if test="cO != null" >
        #{cO,jdbcType=VARCHAR},
      </if>
      <if test="o3 != null" >
        #{o3,jdbcType=VARCHAR},
      </if>
      <if test="pM25 != null" >
        #{pM25,jdbcType=VARCHAR},
      </if>
      <if test="chieflyInfectant != null" >
        #{chieflyInfectant,jdbcType=VARCHAR},
      </if>
      <if test="grade != null" >
        #{grade,jdbcType=VARCHAR},
      </if>
      <if test="gradeDescription != null" >
        #{gradeDescription,jdbcType=NVARCHAR},
      </if>
      <if test="aQI != null" >
        #{aQI,jdbcType=VARCHAR},
      </if>
      <if test="color != null" >
        #{color,jdbcType=NVARCHAR},
      </if>
      <if test="inputdate != null" >
        #{inputdate,jdbcType=TIMESTAMP},
      </if>
    </trim>
  </insert>
  <update id="updateByPrimaryKeySelective" parameterType="xsscd.monitor.air.southwest.modules.job.entitys.mybatis.dto.GWFactCityHour" >
    <!--
      WARNING - @mbggenerated
      This element is automatically generated by MyBatis Generator, do not modify.
    -->
    update GW_Fact_CityHour
    <set >
      <if test="datetime != null" >
        datetime = #{datetime,jdbcType=TIMESTAMP},
      </if>
      <if test="citycode != null" >
        citycode = #{citycode,jdbcType=INTEGER},
      </if>
      <if test="cityname != null" >
        cityname = #{cityname,jdbcType=NVARCHAR},
      </if>
      <if test="stationcount != null" >
        stationcount = #{stationcount,jdbcType=INTEGER},
      </if>
      <if test="sO2 != null" >
        SO2 = #{sO2,jdbcType=VARCHAR},
      </if>
      <if test="nO2 != null" >
        NO2 = #{nO2,jdbcType=VARCHAR},
      </if>
      <if test="pM10 != null" >
        PM10 = #{pM10,jdbcType=VARCHAR},
      </if>
      <if test="cO != null" >
        CO = #{cO,jdbcType=VARCHAR},
      </if>
      <if test="o3 != null" >
        O3 = #{o3,jdbcType=VARCHAR},
      </if>
      <if test="pM25 != null" >
        PM25 = #{pM25,jdbcType=VARCHAR},
      </if>
      <if test="chieflyInfectant != null" >
        Chiefly_Infectant = #{chieflyInfectant,jdbcType=VARCHAR},
      </if>
      <if test="grade != null" >
        Grade = #{grade,jdbcType=VARCHAR},
      </if>
      <if test="gradeDescription != null" >
        GradeDescription = #{gradeDescription,jdbcType=NVARCHAR},
      </if>
      <if test="aQI != null" >
        AQI = #{aQI,jdbcType=VARCHAR},
      </if>
      <if test="color != null" >
        Color = #{color,jdbcType=NVARCHAR},
      </if>
      <if test="inputdate != null" >
        inputdate = #{inputdate,jdbcType=TIMESTAMP},
      </if>
    </set>
    where ID = #{iD,jdbcType=INTEGER}
  </update>
  <update id="updateByPrimaryKey" parameterType="xsscd.monitor.air.southwest.modules.job.entitys.mybatis.dto.GWFactCityHour" >
    <!--
      WARNING - @mbggenerated
      This element is automatically generated by MyBatis Generator, do not modify.
    -->
    update GW_Fact_CityHour
    set datetime = #{datetime,jdbcType=TIMESTAMP},
      citycode = #{citycode,jdbcType=INTEGER},
      cityname = #{cityname,jdbcType=NVARCHAR},
      stationcount = #{stationcount,jdbcType=INTEGER},
      SO2 = #{sO2,jdbcType=VARCHAR},
      NO2 = #{nO2,jdbcType=VARCHAR},
      PM10 = #{pM10,jdbcType=VARCHAR},
      CO = #{cO,jdbcType=VARCHAR},
      O3 = #{o3,jdbcType=VARCHAR},
      PM25 = #{pM25,jdbcType=VARCHAR},
      Chiefly_Infectant = #{chieflyInfectant,jdbcType=VARCHAR},
      Grade = #{grade,jdbcType=VARCHAR},
      GradeDescription = #{gradeDescription,jdbcType=NVARCHAR},
      AQI = #{aQI,jdbcType=VARCHAR},
      Color = #{color,jdbcType=NVARCHAR},
      inputdate = #{inputdate,jdbcType=TIMESTAMP}
    where ID = #{iD,jdbcType=INTEGER}
  </update>
</mapper>