<?xml version="1.0" encoding="UTF-8" ?>
<!DOCTYPE mapper PUBLIC "-//mybatis.org//DTD Mapper 3.0//EN" "http://mybatis.org/dtd/mybatis-3-mapper.dtd" >
<mapper namespace="xsscd.monitor.air.southwest.modules.job.entitys.mybatis.mapper.MediumLongAnalysisParamMapper">
    <resultMap id="BaseResultMap"
               type="xsscd.monitor.air.southwest.modules.job.entitys.mybatis.dto.MediumLongAnalysisParam">
        <!--
          WARNING - @mbggenerated
          This element is automatically generated by MyBatis Generator, do not modify.
        -->
        <id column="id" property="id" jdbcType="BIGINT"/>
        <result column="city" property="city" jdbcType="VARCHAR"/>
        <result column="city_code" property="cityCode" jdbcType="VARCHAR"/>
        <result column="report_time" property="reportTime" jdbcType="TIMESTAMP"/>
        <result column="param" property="param" jdbcType="VARCHAR"/>
        <result column="param_value" property="paramValue" jdbcType="VARCHAR"/>
        <result column="param_value_l" property="paramValueL" jdbcType="VARCHAR"/>
    </resultMap>
    <sql id="Base_Column_List">
        <!--
          WARNING - @mbggenerated
          This element is automatically generated by MyBatis Generator, do not modify.
        -->
        id, city, city_code, report_time, param, param_value,param_value_l
    </sql>
    <sql id="Base_Where_Case">
        <!--
          WARNING - @mbggenerated
          This element is automatically generated by MyBatis Generator, do not modify.
        -->
        <where>
            <if test="id != null">
                AND id = #{id,jdbcType=BIGINT}
            </if>
            <if test="city != null">
                AND city = #{city,jdbcType=VARCHAR}
            </if>
            <if test="cityCode != null">
                AND city_code = #{cityCode,jdbcType=VARCHAR}
            </if>
            <if test="reportTime != null">
                AND report_time = #{reportTime,jdbcType=TIMESTAMP}
            </if>
            <if test="param != null">
                AND param = #{param,jdbcType=VARCHAR}
            </if>
            <if test="paramValue != null">
                AND param_value = #{paramValue,jdbcType=VARCHAR}
            </if>
        </where>
    </sql>
    <sql id="Export_Where_Case">
        <!--
          WARNING - @mbggenerated
          This element is automatically generated by MyBatis Generator, do not modify.
        -->
        <where>
            <if test="city != null">
                AND city = #{city,jdbcType=VARCHAR}
            </if>
            <if test="reportTime != null">
                AND report_time = #{reportTime,jdbcType=TIMESTAMP}
            </if>
            <if test="param != null">
                AND param = #{param,jdbcType=VARCHAR}
            </if>
        </where>
    </sql>
    <select id="selectCount" resultType="java.lang.Long"
            parameterType="xsscd.monitor.air.southwest.modules.job.entitys.mybatis.dto.MediumLongAnalysisParam">
        <!--
          WARNING - @mbggenerated
          This element is automatically generated by MyBatis Generator, do not modify.
        -->
        select count( id)
        from medium_long_analysis_param
        <include refid="Base_Where_Case"/>
    </select>
    <select id="select" resultMap="BaseResultMap"
            parameterType="xsscd.monitor.air.southwest.modules.job.entitys.mybatis.dto.MediumLongAnalysisParam">
        select
        <include refid="Base_Column_List"/>
        from medium_long_analysis_param
        <include refid="Base_Where_Case"/>
    </select>
    <select id="selectExport" resultMap="BaseResultMap"
            parameterType="xsscd.monitor.air.southwest.modules.job.entitys.mybatis.dto.vo.MediumLongVO">
        select
        <include refid="Base_Column_List"/>
        from medium_long_analysis_param
        <include refid="Export_Where_Case"/>
         ORDER BY report_time ASC
    </select>
    <select id="selectByPrimaryKey" resultMap="BaseResultMap" parameterType="java.lang.Long">
        <!--
          WARNING - @mbggenerated
          This element is automatically generated by MyBatis Generator, do not modify.
        -->
        select
        <include refid="Base_Column_List"/>
        from medium_long_analysis_param
        where id = #{id,jdbcType=BIGINT}
    </select>
    <delete id="deleteByPrimaryKey" parameterType="java.lang.Long">
        <!--
          WARNING - @mbggenerated
          This element is automatically generated by MyBatis Generator, do not modify.
        -->
        delete from medium_long_analysis_param
        where id = #{id,jdbcType=BIGINT}
    </delete>
    <insert id="insert"
            parameterType="xsscd.monitor.air.southwest.modules.job.entitys.mybatis.dto.MediumLongAnalysisParam">
        <!--
          WARNING - @mbggenerated
          This element is automatically generated by MyBatis Generator, do not modify.
        -->
        insert into medium_long_analysis_param (id, city, city_code,
        report_time, param, param_value
        )
        values (#{id,jdbcType=BIGINT}, #{city,jdbcType=VARCHAR}, #{cityCode,jdbcType=VARCHAR},
        #{reportTime,jdbcType=TIMESTAMP}, #{param,jdbcType=VARCHAR}, #{paramValue,jdbcType=VARCHAR}
        )
    </insert>
    <insert id="insertSelective"
            parameterType="xsscd.monitor.air.southwest.modules.job.entitys.mybatis.dto.MediumLongAnalysisParam">
        <!--
          WARNING - @mbggenerated
          This element is automatically generated by MyBatis Generator, do not modify.
        -->
        insert into medium_long_analysis_param
        <trim prefix="(" suffix=")" suffixOverrides=",">
            <if test="id != null">
                id,
            </if>
            <if test="city != null">
                city,
            </if>
            <if test="cityCode != null">
                city_code,
            </if>
            <if test="reportTime != null">
                report_time,
            </if>
            <if test="param != null">
                param,
            </if>
            <if test="paramValue != null">
                param_value,
            </if>
        </trim>
        <trim prefix="values (" suffix=")" suffixOverrides=",">
            <if test="id != null">
                #{id,jdbcType=BIGINT},
            </if>
            <if test="city != null">
                #{city,jdbcType=VARCHAR},
            </if>
            <if test="cityCode != null">
                #{cityCode,jdbcType=VARCHAR},
            </if>
            <if test="reportTime != null">
                #{reportTime,jdbcType=TIMESTAMP},
            </if>
            <if test="param != null">
                #{param,jdbcType=VARCHAR},
            </if>
            <if test="paramValue != null">
                #{paramValue,jdbcType=VARCHAR},
            </if>
        </trim>
    </insert>
    <update id="updateByPrimaryKeySelective"
            parameterType="xsscd.monitor.air.southwest.modules.job.entitys.mybatis.dto.MediumLongAnalysisParam">
        <!--
          WARNING - @mbggenerated
          This element is automatically generated by MyBatis Generator, do not modify.
        -->
        update medium_long_analysis_param
        <set>
            <if test="city != null">
                city = #{city,jdbcType=VARCHAR},
            </if>
            <if test="cityCode != null">
                city_code = #{cityCode,jdbcType=VARCHAR},
            </if>
            <if test="reportTime != null">
                report_time = #{reportTime,jdbcType=TIMESTAMP},
            </if>
            <if test="param != null">
                param = #{param,jdbcType=VARCHAR},
            </if>
            <if test="paramValue != null">
                param_value = #{paramValue,jdbcType=VARCHAR},
            </if>
        </set>
        where id = #{id,jdbcType=BIGINT}
    </update>
    <update id="updateByPrimaryKey"
            parameterType="xsscd.monitor.air.southwest.modules.job.entitys.mybatis.dto.MediumLongAnalysisParam">
        <!--
          WARNING - @mbggenerated
          This element is automatically generated by MyBatis Generator, do not modify.
        -->
        update medium_long_analysis_param
        set city = #{city,jdbcType=VARCHAR},
        city_code = #{cityCode,jdbcType=VARCHAR},
        report_time = #{reportTime,jdbcType=TIMESTAMP},
        param = #{param,jdbcType=VARCHAR},
        param_value = #{paramValue,jdbcType=VARCHAR}
        where id = #{id,jdbcType=BIGINT}
    </update>

    <insert id="saveBatch" parameterType="java.util.List">
        INSERT INTO medium_long_analysis_param
        (city,
        city_code,
        report_time,
        forcast_time,
        param,
        param_value,
        param_value_l
        )
        values
        <foreach collection="list" item="bean" index="index" separator=",">
            (
            #{bean.city,jdbcType=VARCHAR},
            #{bean.cityCode,jdbcType=VARCHAR},
            #{bean.reportTime,jdbcType=TIMESTAMP},
            #{bean.forcastTime,jdbcType=TIMESTAMP},
            #{bean.param,jdbcType=VARCHAR},
            #{bean.paramValue,jdbcType=VARCHAR},
            #{bean.paramValueL,jdbcType=VARCHAR}
            )
        </foreach>
    </insert>
</mapper>